arbitrum_huy/__init__.py
arbitrum_huy/main.py
arbitrum_huy-0.0.dist-info/LICENSE
arbitrum_huy-0.0.dist-info/METADATA
arbitrum_huy-0.0.dist-info/WHEEL
arbitrum_huy-0.0.dist-info/top_level.txt
arbitrum_huy-0.0.dist-info/RECORD
