Metadata-Version: 2.1
Name: arbitrum-huy
Version: 0.0
Summary: Gaussian and Binomial distributions
Author-email: qwelijdqw@rambler.ru
License-File: LICENSE
Requires-Dist: requests
